setup.py
nobel/__init__.py
nobel/api.py
nobel/countries.py
nobel/data.py
nobel/laureates.py
nobel/prizes.py
nobel.egg-info/PKG-INFO
nobel.egg-info/SOURCES.txt
nobel.egg-info/dependency_links.txt
nobel.egg-info/requires.txt
nobel.egg-info/top_level.txt