Metadata-Version: 1.1
Name: nobel
Version: 0.1a
Summary: A simple pythonic wrapper for the Nobel Prize API.
Home-page: https://github.com/vibragiel/nobel
Author: Gabriel Rodríguez Alberich
Author-email: gabi@gabi.is
License: Apache Software License
Platform: any
Classifier: Programming Language :: Python
Classifier: Development Status :: 3 - Alpha
Classifier: Natural Language :: English
Classifier: Environment :: Web Environment
Classifier: Intended Audience :: Developers
Classifier: License :: OSI Approved :: Apache Software License
Classifier: Operating System :: OS Independent
Classifier: Topic :: Software Development :: Libraries :: Python Modules
Classifier: Topic :: Internet :: WWW/HTTP :: Dynamic Content
